arbitro_typing/__init__.py
arbitro_typing/data_types.py
arbitro_typing/models/operations.py
arbitro_typing-1.5.0.dist-info/LICENSE
arbitro_typing-1.5.0.dist-info/METADATA
arbitro_typing-1.5.0.dist-info/WHEEL
arbitro_typing-1.5.0.dist-info/RECORD
