Metadata-Version: 2.1
Name: arbitro-typing
Version: 1.5.0
Summary: 
Author: Diego Villegas
Author-email: dvillegas@creasys.cl
Requires-Python: >=3.11,<4.0
Classifier: Programming Language :: Python :: 3
Classifier: Programming Language :: Python :: 3.11
Classifier: Programming Language :: Python :: 3.12
Requires-Dist: pydantic (>=2.7.1,<3.0.0)
Requires-Dist: pymongo (>=4.7.2,<5.0.0)
